VSR/__init__.py
VSR/Backend/__init__.py
VSR/Backend/Keras/__init__.py
VSR/Backend/Keras/Framework/Environment.py
VSR/Backend/Keras/Framework/Trainer.py
VSR/Backend/Keras/Framework/__init__.py
VSR/Backend/Keras/Models/Model.py
VSR/Backend/Keras/Models/Srcnn.py
VSR/Backend/Keras/Models/__init__.py
VSR/Backend/TF/Util.py
VSR/Backend/TF/__init__.py
VSR/Backend/TF/Arch/Dense.py
VSR/Backend/TF/Arch/Discriminator.py
VSR/Backend/TF/Arch/Residual.py
VSR/Backend/TF/Arch/__init__.py
VSR/Backend/TF/Framework/GAN.py
VSR/Backend/TF/Framework/LayersHelper.py
VSR/Backend/TF/Framework/Motion.py
VSR/Backend/TF/Framework/Noise.py
VSR/Backend/TF/Framework/SuperResolution.py
VSR/Backend/TF/Framework/Trainer.py
VSR/Backend/TF/Framework/__init__.py
VSR/Backend/TF/Models/Carn.py
VSR/Backend/TF/Models/Crdn.py
VSR/Backend/TF/Models/Dbpn.py
VSR/Backend/TF/Models/Dcscn.py
VSR/Backend/TF/Models/DnCnn.py
VSR/Backend/TF/Models/Drcn.py
VSR/Backend/TF/Models/Drrn.py
VSR/Backend/TF/Models/Drsr.py
VSR/Backend/TF/Models/Drsr_v2.py
VSR/Backend/TF/Models/Duf.py
VSR/Backend/TF/Models/Edsr.py
VSR/Backend/TF/Models/Espcn.py
VSR/Backend/TF/Models/FFDNet.py
VSR/Backend/TF/Models/Gan.py
VSR/Backend/TF/Models/Idn.py
VSR/Backend/TF/Models/LapSrn.py
VSR/Backend/TF/Models/MemNet.py
VSR/Backend/TF/Models/Msrn.py
VSR/Backend/TF/Models/Nlrn.py
VSR/Backend/TF/Models/Rcan.py
VSR/Backend/TF/Models/Rdn.py
VSR/Backend/TF/Models/SRDenseNet.py
VSR/Backend/TF/Models/SRFeat.py
VSR/Backend/TF/Models/SrGan.py
VSR/Backend/TF/Models/Srcnn.py
VSR/Backend/TF/Models/Vdsr.py
VSR/Backend/TF/Models/Vespcn.py
VSR/Backend/TF/Models/__init__.py
VSR/Backend/Torch/__init__.py
VSR/Backend/Torch/Framework/Environment.py
VSR/Backend/Torch/Framework/Summary.py
VSR/Backend/Torch/Framework/Trainer.py
VSR/Backend/Torch/Framework/__init__.py
VSR/Backend/Torch/Models/Bicubic.py
VSR/Backend/Torch/Models/Carn.py
VSR/Backend/Torch/Models/Classic.py
VSR/Backend/Torch/Models/Crdn.py
VSR/Backend/Torch/Models/Dbpn.py
VSR/Backend/Torch/Models/Drn.py
VSR-1.0.6.1.dist-info/LICENSE
VSR-1.0.6.1.dist-info/METADATA
VSR-1.0.6.1.dist-info/WHEEL
VSR-1.0.6.1.dist-info/top_level.txt
VSR-1.0.6.1.dist-info/RECORD
