Metadata-Version: 2.1
Name: VSR
Version: 1.0.6.1
Summary: Video Super-Resolution Framework
Home-page: https://github.com/LoSealL/VideoSuperResolution
Author: Wenyi Tang
Author-email: wenyitang@outlook.com
License: MIT
Keywords: super-resolution sr vsr cnn srcnn vespcn
Platform: UNKNOWN
Classifier: Programming Language :: Python :: 3
Classifier: License :: OSI Approved :: MIT License
Classifier: Operating System :: OS Independent
Requires-Python: >=3.6
Requires-Dist: numpy
Requires-Dist: scipy
Requires-Dist: scikit-image
Requires-Dist: matplotlib
Requires-Dist: pillow
Requires-Dist: pypng
Requires-Dist: pytest
Requires-Dist: PyYAML
Requires-Dist: psutil
Requires-Dist: tqdm
Requires-Dist: h5py
Requires-Dist: easydict (>=1.9)
